{
    "id": "https://osmt.wgu.edu/api/skills/c937c110-91f5-4a47-8a26-090418610690",
    "status": "published",
    "uuid": "c937c110-91f5-4a47-8a26-090418610690",
    "skillName": "AI-generated Solutions Interpretation and Implementation",
    "skillStatement": "Interpret AI-generated solutions and how to implement them effectively.",
    "keywords": [
        "Problem-Solving",
        "Artificial Intelligence"
    ],
    "occupations": [],
    "publishDate": "2023-06-15T00:47:50.466175",
    "archiveDate": null,
    "category": "Artificial Intelligence (AI)"
}