{
    "id": "https://osmt.wgu.edu/api/skills/423124e1-9732-49d7-9633-cc140498de4d",
    "status": "published",
    "uuid": "423124e1-9732-49d7-9633-cc140498de4d",
    "skillName": "Object Creation",
    "skillStatement": "Differentiate between classes and objects.",
    "keywords": [
        "OOP",
        "Java (Programming Language)",
        "classes",
        "objects",
        "WGUSID: 12294"
    ],
    "occupations": [
        {
            "code": "11-3130",
            "targetNodeName": "Training and Development Managers",
            "frameworkName": "bls"
        },
        {
            "code": "11-3131",
            "targetNodeName": "Training and Development Managers",
            "frameworkName": "bls"
        },
        {
            "code": "15-0000",
            "targetNodeName": "Computer and Mathematical Occupations",
            "frameworkName": "bls"
        }
    ],
    "publishDate": "2022-02-10T20:37:13.051074",
    "archiveDate": null,
    "category": "Java (Programming Language)"
}